ami_client/__init__.py
ami_client/__version__.py
ami_client/_ami_client.py
ami_client/operation/__init__.py
ami_client/operation/_base.py
ami_client/operation/action/__init__.py
ami_client/operation/action/_base.py
ami_client/operation/action/core_status.py
ami_client/operation/action/login.py
ami_client/operation/action/logoff.py
ami_client/operation/action/originate.py
ami_client/operation/action/ping.py
ami_client/operation/event/__init__.py
ami_client/operation/event/_base.py
ami_client/operation/event/agent.py
ami_client/operation/event/agi.py
ami_client/operation/event/alarm.py
ami_client/operation/event/aoc.py
ami_client/operation/event/aor.py
ami_client/operation/event/async_agi.py
ami_client/operation/event/auth.py
ami_client/operation/event/hangup.py
ami_client/operation/event/newexten.py
ami_client/operation/event/queue.py
ami_client/operation/event/varset.py
ami_client/operation/response/__init__.py
ami_client/operation/response/_base.py
ami_client/operation/response/error.py
ami_client/operation/response/success.py
py_ami_client-0.2.1.dist-info/licenses/LICENSE
py_ami_client-0.2.1.dist-info/METADATA
py_ami_client-0.2.1.dist-info/WHEEL
py_ami_client-0.2.1.dist-info/top_level.txt
py_ami_client-0.2.1.dist-info/RECORD
