Metadata-Version: 2.4
Name: py-ami-client
Version: 0.2.1
Summary: Python Asterisk Management Interface Client
Home-page: https://github.com/Radin-System/py-ami-client
Author: Radin-System
Author-email: hmohammad2520-org <hmohammad2520@gmail.com>
License: MIT License
Project-URL: Homepage, https://github.com/hmohammad2520-org/py-ami-client
Project-URL: BugTracker, https://github.com/hmohammad2520-org/py-ami-client/issues
Keywords: python,library,asterisk,ami
Classifier: Programming Language :: Python :: 3
Classifier: License :: OSI Approved :: MIT License
Classifier: Operating System :: OS Independent
Requires-Python: >=3.9
License-File: LICENSE
Requires-Dist: classmods==1.2.1
Dynamic: author
Dynamic: home-page
Dynamic: license-file
